swanculler/__init__.py
swanculler/__main__.py
swanculler/_version.py
swanculler/app.py
swanculler-1.0.5.dist-info/METADATA
swanculler-1.0.5.dist-info/WHEEL
swanculler-1.0.5.dist-info/entry_points.txt
swanculler-1.0.5.dist-info/top_level.txt
swanculler-1.0.5.dist-info/RECORD
