Metadata-Version: 2.4
Name: swanculler
Version: 1.0.5
Summary: Culler for JupyterHub
Home-page: https://github.com/swan-cern/jupyterhub-extensions
Author: SWAN Admins
License: AGPL-3.0
Keywords: JupyterHub,SWAN,CERN
Platform: Linux
Platform: Mac OS X
Classifier: License :: OSI Approved :: GNU Affero General Public License v3
Classifier: Intended Audience :: Developers
Classifier: Intended Audience :: System Administrators
Classifier: Intended Audience :: Science/Research
Classifier: Programming Language :: Python
Classifier: Programming Language :: Python :: 3
Requires-Dist: tornado
Requires-Dist: python-dateutil
Dynamic: author
Dynamic: classifier
Dynamic: description
Dynamic: description-content-type
Dynamic: home-page
Dynamic: keywords
Dynamic: license
Dynamic: platform
Dynamic: requires-dist
Dynamic: summary
